__init__.py
devcp
setup.py
jld/TODO
jld/__init__.py
jld.egg-info/PKG-INFO
jld.egg-info/SOURCES.txt
jld.egg-info/dependency_links.txt
jld.egg-info/not-zip-safe
jld.egg-info/requires.txt
jld.egg-info/top_level.txt
jld/backup/scripts/dlc
jld/backup/scripts/dlc.bat
jld/backup/scripts/dlc.py
jld/backup/scripts/glf
jld/backup/scripts/glf.bat
jld/backup/scripts/glf.py
jld/backup/scripts/mm
jld/backup/scripts/mm.bat
jld/backup/scripts/mm.py
jld/cmd/pypre.py
jld/scripts/trns.py
jld/api/__init__.py
jld/api/delicious.py
jld/api/delicious_objects.py
jld/api/gliffy.py
jld/api/mindmeister.py
jld/api/mindmeister_response.py
jld/backup/__init__.py
jld/backup/delicious.py
jld/backup/delicious_backup.py
jld/backup/delicious_db.py
jld/backup/delicious_defaults.py
jld/backup/delicious_defaults.yaml
jld/backup/delicious_messages.py
jld/backup/delicious_messages.yaml
jld/backup/delicious_printer.py
jld/backup/delicious_ui.py
jld/backup/gliffy.py
jld/backup/gliffy_backup.py
jld/backup/gliffy_db.py
jld/backup/gliffy_defaults.py
jld/backup/gliffy_defaults.yaml
jld/backup/gliffy_messages.py
jld/backup/gliffy_messages.yaml
jld/backup/gliffy_printer.py
jld/backup/gliffy_ui.py
jld/backup/mindmeister_backup.py
jld/backup/mindmeister_db.py
jld/backup/mindmeister_defaults.py
jld/backup/mindmeister_defaults.yaml
jld/backup/mindmeister_messages.py
jld/backup/mindmeister_messages.yaml
jld/backup/mindmeister_printer.py
jld/backup/mindmeister_ui.py
jld/backup/mm.py
jld/backup/mmd.py
jld/backup/scripts/dlc
jld/backup/scripts/dlc.bat
jld/backup/scripts/dlc.py
jld/backup/scripts/glf
jld/backup/scripts/glf.bat
jld/backup/scripts/glf.py
jld/backup/scripts/mm
jld/backup/scripts/mm.bat
jld/backup/scripts/mm.py
jld/cmd/__init__.py
jld/cmd/base.tpl
jld/cmd/nsvn.py
jld/cmd/pypre.py
jld/cmd/test.tpl
jld/cmd_g2/__init__.py
jld/cmd_g2/base_ui.py
jld/cmd_g2/transmission/__init__.py
jld/cmd_g2/transmission/cmd.py
jld/cmd_g2/transmission/defaults.yaml
jld/cmd_g2/transmission/messages.yaml
jld/cmd_g2/transmission/trns.py
jld/gdata/__init__.py
jld/gdata/docs.py
jld/registry/__init__.py
jld/registry/exception.py
jld/registry/linux.py
jld/registry/windows.py
jld/scripts/trns.py
