Metadata-Version: 1.0
Name: jld
Version: 0.0.39
Summary:  Jean-Lou Dupont's Python Library - WEB API & command line tools
Home-page: http://www.jldupont.com/doc/lib/jld/
Author: Jean-Lou Dupont
Author-email: python@jldupont.com
License: UNKNOWN
Platform: UNKNOWN
Classifier: Development Status :: 3 - Alpha
Classifier: Intended Audience :: Developers
Classifier: License :: Public Domain
Classifier: Programming Language :: Python
Classifier: Topic :: Software Development :: Libraries :: Python Modules
Classifier: Operating System :: Microsoft :: Windows
Classifier: Operating System :: POSIX
